abtf_wrapper/__init__.py
abtf_wrapper/autobot_tf.py
abtf_wrapper/models/__init__.py
abtf_wrapper/models/all.py
abtf_wrapper/models/econ_item.py
abtf_wrapper/models/item_object.py
abtf_wrapper/models/items_game.py
abtf_wrapper/models/schema.py
abtf_wrapper-1.0.0.dist-info/LICENSE
abtf_wrapper-1.0.0.dist-info/METADATA
abtf_wrapper-1.0.0.dist-info/WHEEL
abtf_wrapper-1.0.0.dist-info/RECORD
