Metadata-Version: 2.1
Name: abtf_wrapper
Version: 1.0.0
Summary: 
Author: Reue Munz
Author-email: tt574@proton.me
Requires-Python: >=3.12,<4.0
Classifier: Programming Language :: Python :: 3
Classifier: Programming Language :: Python :: 3.12
Requires-Dist: pydantic (>=2.9.2,<3.0.0)
Requires-Dist: requests (>=2.32.3,<3.0.0)
